Metadata-Version: 2.1
Name: seiRJ
Version: 1.0.2
Summary: Acesso ao SEI-RJ
Home-page: https://github.com/joaocampbell2
Author: Joao Campbell
Author-email: jpcampbell2004@gmail.com
License: MIT
Project-URL: Código fonte, https://github.com/joaocampbell2
Project-URL: Download, https://github.com/joaocampbell2
Keywords: seiRJ
Classifier: Development Status :: 5 - Production/Stable
Classifier: Intended Audience :: Developers
Classifier: License :: OSI Approved :: MIT License
Classifier: Natural Language :: Portuguese (Brazilian)
Classifier: Operating System :: OS Independent
Classifier: Topic :: Software Development :: Internationalization
Classifier: Topic :: Scientific/Engineering :: Physics
License-File: LICENSE.txt
